[{"id":"1805010","nama":"PADANG RATU"},{"id":"1805011","nama":"SELAGAI LINGGA"},{"id":"1805012","nama":"PUBIAN"},{"id":"1805013","nama":"ANAK TUHA"},{"id":"1805014","nama":"ANAK RATU AJI"},{"id":"1805020","nama":"KALIREJO"},{"id":"1805021","nama":"SENDANG AGUNG"},{"id":"1805030","nama":"BANGUNREJO"},{"id":"1805040","nama":"GUNUNG SUGIH"},{"id":"1805041","nama":"BEKRI"},{"id":"1805042","nama":"BUMI RATU NUBAN"},{"id":"1805050","nama":"TRIMURJO"},{"id":"1805060","nama":"PUNGGUR"},{"id":"1805061","nama":"KOTA GAJAH"},{"id":"1805070","nama":"SEPUTIH RAMAN"},{"id":"1805080","nama":"TERBANGGI BESAR"},{"id":"1805081","nama":"SEPUTIH AGUNG"},{"id":"1805082","nama":"WAY PENGUBUAN"},{"id":"1805090","nama":"TERUSAN NUNYAI"},{"id":"1805100","nama":"SEPUTIH MATARAM"},{"id":"1805101","nama":"BANDAR MATARAM"},{"id":"1805110","nama":"SEPUTIH BANYAK"},{"id":"1805111","nama":"WAY SEPUTIH"},{"id":"1805120","nama":"RUMBIA"},{"id":"1805121","nama":"BUMI NABUNG"},{"id":"1805122","nama":"PUTRA RUMBIA"},{"id":"1805130","nama":"SEPUTIH SURABAYA"},{"id":"1805131","nama":"BANDAR SURABAYA"}]