[{"id":"190301","nama":"Toboali","latitude":-2.9111582797,"longitude":106.5090323712},{"id":"190302","nama":"Lepar Pongok","latitude":-2.9579751525,"longitude":106.8120522537},{"id":"190303","nama":"Air Gegas","latitude":-2.7190931869,"longitude":106.3739146347},{"id":"190304","nama":"Simpang Rimba","latitude":-2.6511400536,"longitude":105.9830032191},{"id":"190305","nama":"Payung","latitude":-2.6236462378,"longitude":106.1384497485},{"id":"190306","nama":"Tukak Sadai","latitude":-3.024885988,"longitude":106.6660872104},{"id":"190307","nama":"Pulaubesar","latitude":-2.8007649897,"longitude":106.1396158637},{"id":"190308","nama":"Kepulauan Pongok","latitude":-2.8717999137,"longitude":107.059807269}]