[{"id":"3322010","nama":"GETASAN"},{"id":"3322020","nama":"TENGARAN"},{"id":"3322030","nama":"SUSUKAN"},{"id":"3322031","nama":"KALIWUNGU"},{"id":"3322040","nama":"SURUH"},{"id":"3322050","nama":"PABELAN"},{"id":"3322060","nama":"TUNTANG"},{"id":"3322070","nama":"BANYUBIRU"},{"id":"3322080","nama":"JAMBU"},{"id":"3322090","nama":"SUMOWONO"},{"id":"3322100","nama":"AMBARAWA"},{"id":"3322101","nama":"BANDUNGAN"},{"id":"3322110","nama":"BAWEN"},{"id":"3322120","nama":"BRINGIN"},{"id":"3322121","nama":"BANCAK"},{"id":"3322130","nama":"PRINGAPUS"},{"id":"3322140","nama":"BERGAS"},{"id":"3322151","nama":"UNGARAN BARAT"},{"id":"3322152","nama":"UNGARAN TIMUR"}]