[{"id":"3511010","nama":"MAESAN"},{"id":"3511020","nama":"GRUJUGAN"},{"id":"3511030","nama":"TAMANAN"},{"id":"3511031","nama":"JAMBESARI DARUS SHOLAH"},{"id":"3511040","nama":"PUJER"},{"id":"3511050","nama":"TLOGOSARI"},{"id":"3511060","nama":"SUKOSARI"},{"id":"3511061","nama":"SUMBER WRINGIN"},{"id":"3511070","nama":"TAPEN"},{"id":"3511080","nama":"WONOSARI"},{"id":"3511090","nama":"TENGGARANG"},{"id":"3511100","nama":"BONDOWOSO"},{"id":"3511110","nama":"CURAH DAMI"},{"id":"3511111","nama":"BINAKAL"},{"id":"3511120","nama":"PAKEM"},{"id":"3511130","nama":"WRINGIN"},{"id":"3511140","nama":"TEGALAMPEL"},{"id":"3511141","nama":"TAMAN KROCOK"},{"id":"3511150","nama":"KLABANG"},{"id":"3511151","nama":"SEMPOL"},{"id":"3511152","nama":"BOTOLINGGO"},{"id":"3511160","nama":"PRAJEKAN"},{"id":"3511170","nama":"CERMEE"}]