[{"id":"530501","nama":"Teluk Mutiara","latitude":-8.2286890707,"longitude":124.541852795},{"id":"530502","nama":"Alor Barat Laut","latitude":-8.199326107,"longitude":124.4516772266},{"id":"530503","nama":"Alor Barat Daya","latitude":-8.3388960136,"longitude":124.4709160217},{"id":"530504","nama":"Alor Selatan","latitude":-8.3305816618,"longitude":124.7317051082},{"id":"530505","nama":"Alor Timur","latitude":-8.2466315264,"longitude":125.0065044597},{"id":"530506","nama":"Pantar","latitude":-8.2549203417,"longitude":124.2399577637},{"id":"530507","nama":"Alor Tengah Utara","latitude":-8.2375648933,"longitude":124.6363352514},{"id":"530508","nama":"Alor Timur Laut","latitude":-8.2266264231,"longitude":124.8047626625},{"id":"530509","nama":"Pantar Barat","latitude":-8.3516177008,"longitude":124.0691644398},{"id":"530510","nama":"Kabola","latitude":-8.1597039713,"longitude":124.5542667037},{"id":"530511","nama":"Pulau Pura","latitude":-8.3006048689,"longitude":124.3460153921},{"id":"530512","nama":"Mataru","latitude":-8.3641447746,"longitude":124.6347843803},{"id":"530513","nama":"Pureman","latitude":-8.3360330843,"longitude":124.8828814841},{"id":"530514","nama":"Pantar Timur","latitude":-8.3291183809,"longitude":124.2403246796},{"id":"530515","nama":"Lembur","latitude":-8.1985648355,"longitude":124.7169322221},{"id":"530516","nama":"Pantar Tengah","latitude":-8.4536380014,"longitude":124.1226028849},{"id":"530517","nama":"Pantar Baru Laut","latitude":-8.3808496493,"longitude":123.968142243}]