[{"id":"760501","nama":"Banggae","latitude":-3.5371479663,"longitude":118.9447166523},{"id":"760502","nama":"Pamboang","latitude":-3.4650676032,"longitude":118.9123674425},{"id":"760503","nama":"Sendana","latitude":-3.3381698307,"longitude":118.8874301533},{"id":"760504","nama":"Malunda","latitude":-2.9781839409,"longitude":118.9408673398},{"id":"760505","nama":"Ulumanda","latitude":-3.0792036975,"longitude":118.9428803581},{"id":"760506","nama":"Tammerodo Sendana","latitude":-3.2241463978,"longitude":118.8696106249},{"id":"760507","nama":"Tubo Sendana","latitude":-3.1291276935,"longitude":118.8204344955},{"id":"760508","nama":"Banggae Timur","latitude":-3.5131896646,"longitude":118.9677023673}]