[{"id":"920301","nama":"Fak-Fak"},{"id":"920302","nama":"Fak-Fak Barat"},{"id":"920303","nama":"Fak-Fak Timur"},{"id":"920304","nama":"Kokas"},{"id":"920305","nama":"Fak-Fak Tengah"},{"id":"920306","nama":"Karas"},{"id":"920307","nama":"Bomberay"},{"id":"920308","nama":"Kramongmongga"},{"id":"920309","nama":"Teluk Patipi"},{"id":"920310","nama":"Pariwari"},{"id":"920311","nama":"Wartutin"},{"id":"920312","nama":"Fakfak Timur Tengah"},{"id":"920313","nama":"Arguni"},{"id":"920314","nama":"Mbahamdandara"},{"id":"920315","nama":"Kayauni"},{"id":"920316","nama":"Furwagi"},{"id":"920317","nama":"Tomage"}]