[{"id":"1103232001","nama":"Keutapang Dua","latitude":4.9219611889,"longitude":97.79664883},{"id":"1103232002","nama":"Matang Rayeuk PP","latitude":4.9368261776,"longitude":97.79886107},{"id":"1103232003","nama":"Meunasah Jeumpa","latitude":4.9214133669,"longitude":97.7831952095},{"id":"1103232004","nama":"Lhok Asahan","latitude":4.9106288611,"longitude":97.7927284538},{"id":"1103232005","nama":"Tualang Dalam","latitude":4.9127281263,"longitude":97.7835093561},{"id":"1103232006","nama":"Seuneubok Kuyun","latitude":4.8755100684,"longitude":97.7812225257},{"id":"1103232007","nama":"Ulee Glee","latitude":4.8958327761,"longitude":97.7941226365},{"id":"1103232008","nama":"Seuneubok  Barat","latitude":4.9199699036,"longitude":97.8013417734},{"id":"1103232009","nama":"Seuneubok  Teungoh","latitude":4.9163481362,"longitude":97.8057472489},{"id":"1103232010","nama":"Seuneubok  Timu","latitude":4.9125823459,"longitude":97.8103265539},{"id":"1103232011","nama":"Matang Bungong","latitude":4.9281674323,"longitude":97.8082066694},{"id":"1103232012","nama":"Matang Rayeuk SMK","latitude":4.9216405176,"longitude":97.8158598931},{"id":"1103232013","nama":"Seuneubok  Dalam","latitude":4.9039358173,"longitude":97.8009870757}]