[{"id":"1111062001","nama":"TANJONG SEURUEKUY"},{"id":"1111062002","nama":"ALUE RIMEE"},{"id":"1111062003","nama":"PAYA LUENG JALO"},{"id":"1111062004","nama":"SERDANG"},{"id":"1111062005","nama":"ULEE BLANG"},{"id":"1111062006","nama":"MEUNYE VII"},{"id":"1111062007","nama":"PUCOK ALUE PIRAK"},{"id":"1111062008","nama":"ARA TONTON MONCRANG"},{"id":"1111062009","nama":"BILI BARO"},{"id":"1111062010","nama":"KEUTAPANG"},{"id":"1111062011","nama":"RENGKAM"},{"id":"1111062012","nama":"TEUPIN U"},{"id":"1111062013","nama":"ALUE BUNGKOH"},{"id":"1111062014","nama":"CEUMEUCET"},{"id":"1111062015","nama":"LEUPE"},{"id":"1111062016","nama":"TRIENG KRUENG KREH"},{"id":"1111062017","nama":"MATANG KEH"},{"id":"1111062018","nama":"KRUENG PIRAK"},{"id":"1111062019","nama":"RAYEUK PANGE"},{"id":"1111062020","nama":"BUNGONG"},{"id":"1111062021","nama":"GEULUMPANG"},{"id":"1111062022","nama":"ASAN KRUENG KREH"},{"id":"1111062023","nama":"BEURACAN RATA"}]