[{"id":"1117012001","nama":"Blang Rakal"},{"id":"1117012002","nama":"Negeri Antara"},{"id":"1117012003","nama":"Alur Cincin"},{"id":"1117012004","nama":"Pantan Sinaku"},{"id":"1117012005","nama":"Bintang Berangun"},{"id":"1117012006","nama":"Taman Firdaus"},{"id":"1117012007","nama":"Uning Mas"},{"id":"1117012008","nama":"Perdamaian"},{"id":"1117012009","nama":"Ulu Naron"},{"id":"1117012010","nama":"Pantan Lah"},{"id":"1117012011","nama":"Pancar Jelobok"},{"id":"1117012012","nama":"Alur Gading"},{"id":"1117012013","nama":"Rime Raya"},{"id":"1117012014","nama":"Singah Mulo"},{"id":"1117012015","nama":"Simpang Lancang"},{"id":"1117012016","nama":"Wih Porak"},{"id":"1117012017","nama":"Bener Meriah"},{"id":"1117012018","nama":"Musara 58"},{"id":"1117012019","nama":"Musara Pakat"},{"id":"1117012020","nama":"Rata Ara"},{"id":"1117012021","nama":"Gemasih"},{"id":"1117012022","nama":"Pulo Intan"},{"id":"1117012023","nama":"Blang Ara"}]