[{"id":"1206050004","nama":"LUMBAN RAU BARAT"},{"id":"1206050005","nama":"LUMBAN RAU SELATAN"},{"id":"1206050009","nama":"PARSOBURAN TENGAH"},{"id":"1206050010","nama":"PARSOBURAN BARAT"},{"id":"1206050011","nama":"LUMBAN BALIK"},{"id":"1206050012","nama":"LUMBAN PINASA"},{"id":"1206050013","nama":"PANAMPARAN"},{"id":"1206050014","nama":"LUMBAN RUHAP"},{"id":"1206050015","nama":"LUMBAN PEA"},{"id":"1206050016","nama":"HITETANO"},{"id":"1206050018","nama":"LOBU HOLE"},{"id":"1206050019","nama":"BATU NABOLON"},{"id":"1206050020","nama":"LUMBAN GAOL"},{"id":"1206050021","nama":"TORNAGODANG"},{"id":"1206050022","nama":"TAONMARISI"},{"id":"1206050023","nama":"PAGAR BATU"},{"id":"1206050024","nama":"SIBUNTUON"},{"id":"1206050025","nama":"AEK ULOK"},{"id":"1206050026","nama":"PANGUJUNGAN"},{"id":"1206050027","nama":"LUMBAN PINASA SAROHA"},{"id":"1206050028","nama":"LUMBAN LINTONG"},{"id":"1206050029","nama":"PARARUNGAN"}]