[{"id":"1207042001","nama":"Suka Makmur"},{"id":"1207042002","nama":"Namo Mirik"},{"id":"1207042003","nama":"Suka Dame"},{"id":"1207042004","nama":"Pasar X"},{"id":"1207042005","nama":"Perpanden"},{"id":"1207042006","nama":"Kutalimbaru"},{"id":"1207042007","nama":"Sampe Cita"},{"id":"1207042008","nama":"Suka Rende"},{"id":"1207042009","nama":"Kwala Lau Bicik"},{"id":"1207042010","nama":"Lau Bakeni"},{"id":"1207042011","nama":"Silebo Lebo"},{"id":"1207042012","nama":"Sawit Rejo"},{"id":"1207042013","nama":"Namo Rube Julu"},{"id":"1207042014","nama":"Sei Mencirim"}]