[{"id":"1216092001","nama":"Purba Bersatu"},{"id":"1216092002","nama":"Purba Baringin"},{"id":"1216092003","nama":"Karya"},{"id":"1216092004","nama":"Manalu"},{"id":"1216092005","nama":"Sijarango"},{"id":"1216092006","nama":"Tukka Dolok"},{"id":"1216092007","nama":"Siambaton"},{"id":"1216092008","nama":"Parmonangan"},{"id":"1216092009","nama":"Sipagabu"},{"id":"1216092010","nama":"Banuarea"},{"id":"1216092011","nama":"Rura Tanjung"},{"id":"1216092012","nama":"Rura Aek Sopang"},{"id":"1216092013","nama":"Lumban Tonga-Tonga"},{"id":"1216092014","nama":"Pulo Godang"},{"id":"1216092015","nama":"Pakkat Hauagong"},{"id":"1216092016","nama":"Peadungdung"},{"id":"1216092017","nama":"Sijarango I"},{"id":"1216092018","nama":"Ambobi Paranginan"},{"id":"1216092019","nama":"Purba Sianjur"},{"id":"1216092020","nama":"Siambaton Pahae"},{"id":"1216092021","nama":"Panggugunan"},{"id":"1216092022","nama":"Hauagong"}]