[{"id":"1409102001","nama":"Perhentian Luas"},{"id":"1409102002","nama":"Logas"},{"id":"1409102003","nama":"Lubuk Kebun"},{"id":"1409102004","nama":"Sungai Rambai"},{"id":"1409102005","nama":"Situgal"},{"id":"1409102006","nama":"Rambahan"},{"id":"1409102007","nama":"Teratak Rendah"},{"id":"1409102008","nama":"Sikijang"},{"id":"1409102009","nama":"Sukaraja"},{"id":"1409102010","nama":"Sako Margasari"},{"id":"1409102011","nama":"Kuantan Sako"},{"id":"1409102012","nama":"Hulu Teso"},{"id":"1409102013","nama":"Giri Sako"},{"id":"1409102014","nama":"Bumi Mulya"},{"id":"1409102015","nama":"Sidodadi"}]