[{"id":"1502162001","nama":"Muaro Panco Barat"},{"id":"1502162002","nama":"Talang Segegah"},{"id":"1502162003","nama":"Durian Batakuk"},{"id":"1502162004","nama":"Muara Bantan"},{"id":"1502162005","nama":"Parit Ujung Tanjung"},{"id":"1502162006","nama":"Guguk"},{"id":"1502162007","nama":"Markeh"},{"id":"1502162008","nama":"Air Batu"},{"id":"1502162009","nama":"Marus Jaya"},{"id":"1502162010","nama":"Renah Medan"},{"id":"1502162011","nama":"Simpang Parit"},{"id":"1502162012","nama":"Muaro Panco Timur"}]