[{"id":"1502051001","nama":"TALANG SEGEGAH"},{"id":"1502051002","nama":"DURIAN BATAKUK"},{"id":"1502051003","nama":"MUARO PANCO BARAT"},{"id":"1502051004","nama":"PARIT UJUNG TANJUNG"},{"id":"1502051005","nama":"GUGUK"},{"id":"1502051006","nama":"MUARA BANTAN"},{"id":"1502051007","nama":"MARKEH"},{"id":"1502051008","nama":"AIR BATU"},{"id":"1502051009","nama":"MUARO PANCO TIMUR"},{"id":"1502051010","nama":"SIMPANG PARIT"},{"id":"1502051011","nama":"MARUS JAYA"},{"id":"1502051012","nama":"RENAH MEDAN"}]