[{"id":"1503010001","nama":"SIMPANG NARSO"},{"id":"1503010002","nama":"BATU EMPANG"},{"id":"1503010003","nama":"BATIN PENGAMBANG"},{"id":"1503010004","nama":"MUARA AIR DUA"},{"id":"1503010005","nama":"SUNGAI KERADAK"},{"id":"1503010006","nama":"TAMBAK RATU"},{"id":"1503010007","nama":"RANTAU PANJANG"},{"id":"1503010008","nama":"PEKAN GEDANG"},{"id":"1503010009","nama":"PULAU SALAK BARU"},{"id":"1503010010","nama":"BUKIT KALIMAU ULU"},{"id":"1503010011","nama":"RADEN ANOM"},{"id":"1503010012","nama":"DATUK NAN DUO"},{"id":"1503010013","nama":"PADANG JERING"},{"id":"1503010014","nama":"KASIRO"},{"id":"1503010015","nama":"KASIRO ILIR"},{"id":"1503010016","nama":"SUNGAI BEMBAN"},{"id":"1503010017","nama":"SUNGAI BAUNG"},{"id":"1503010018","nama":"MUARA CUBAN"},{"id":"1503010019","nama":"LUBUK BANGKAR"},{"id":"1503010020","nama":"MUARA PEMUAT"},{"id":"1503010021","nama":"BUKITSULAH"},{"id":"1503010022","nama":"PANIBAN BARU"},{"id":"1503010023","nama":"BUKIT BERANTAI"}]