[{"id":"1604112001","nama":"LUBUK NAMBULAN"},{"id":"1604112002","nama":"GELUMBANG"},{"id":"1604112003","nama":"GUNUNG AJI"},{"id":"1604112004","nama":"BINJAI"},{"id":"1604112005","nama":"SENDAWAR"},{"id":"1604112006","nama":"GUNUNG KEMBANG"},{"id":"1604112007","nama":"BUNGA MAS"},{"id":"1604112008","nama":"LUBUK LAYANG ILIR"},{"id":"1604112009","nama":"LUBUK LAYANG ULU"},{"id":"1604112010","nama":"MUARA DANAU"},{"id":"1604112011","nama":"PADURAKSA"},{"id":"1604112012","nama":"GUNUNG KARTO"},{"id":"1604112013","nama":"KARANG ENDAH"},{"id":"1604112014","nama":"PETIKAL BARU"},{"id":"1604112015","nama":"TANDA RAJA"},{"id":"1604112016","nama":"PETIKAL LAMA"},{"id":"1604112017","nama":"MUARA EMPAYANG"},{"id":"1604112018","nama":"LUBUK KUTA"},{"id":"1604112019","nama":"SERONGGO"},{"id":"1604112020","nama":"GEDUNG AGUNG"},{"id":"1604112021","nama":"LUBUK TAMPANG"},{"id":"1604112022","nama":"CECAR"},{"id":"1604112023","nama":"DATAR SERDANG"},{"id":"1604112024","nama":"BATU URIP"},{"id":"1604112025","nama":"TANJUNG BINDU"},{"id":"1604112026","nama":"BABAT LAMA"},{"id":"1604112027","nama":"LINGGAR JAYA"},{"id":"1604112028","nama":"MARGA MULIA"},{"id":"1604112029","nama":"KENCANA SARI"},{"id":"1604112030","nama":"PURWA RAJA"},{"id":"1604112031","nama":"CEMPAKA SAKTI"},{"id":"1604112032","nama":"SUKOHARJO"}]