[{"id":"1607072001","nama":"Muara Padang"},{"id":"1607072002","nama":"Tanjungbaru"},{"id":"1607072003","nama":"Karang Anyar"},{"id":"1607072006","nama":"Purwodadi"},{"id":"1607072007","nama":"Sumber Makmur"},{"id":"1607072008","nama":"Air Gading"},{"id":"1607072009","nama":"Tirto Raharjo"},{"id":"1607072010","nama":"Daya Utama"},{"id":"1607072011","nama":"Daya Makmur"},{"id":"1607072012","nama":"Sido Mulyo 18"},{"id":"1607072013","nama":"Sido Rejo"},{"id":"1607072018","nama":"Sido Mulyo 20"},{"id":"1607072037","nama":"Margo Mulyo 20"},{"id":"1607072038","nama":"Margo Sugihan"},{"id":"1607072042","nama":"Tirta Jaya"}]