[{"id":"1609102001","nama":"Balayan"},{"id":"1609102002","nama":"Berasang"},{"id":"1609102003","nama":"Tebat Gabus"},{"id":"1609102004","nama":"Padang Lay"},{"id":"1609102005","nama":"Danau Rata"},{"id":"1609102006","nama":"Pajar Bulan"},{"id":"1609102007","nama":"Bandar Alam Lama"},{"id":"1609102008","nama":"Muara Payang"},{"id":"1609102009","nama":"Siring Agung"},{"id":"1609102010","nama":"Kota Padang"},{"id":"1609102011","nama":"Padang Bindu"},{"id":"1609102012","nama":"Tenang"},{"id":"1609102013","nama":"Gunung Megang"},{"id":"1609102014","nama":"Ulak Pandan"},{"id":"1609102015","nama":"Pulau Panggung"},{"id":"1609102016","nama":"Simpang Tiga"},{"id":"1609102017","nama":"Simpang Empat"},{"id":"1609102018","nama":"Singa Laga"},{"id":"1609102019","nama":"Air Alun"}]