[{"id":"1808041009","nama":"Taman Asri"},{"id":"1808041015","nama":"Tiuh Balak Pasar"},{"id":"1808041016","nama":"Campur Asri"},{"id":"1808042001","nama":"Setia Negara"},{"id":"1808042002","nama":"Gedung Pakuon"},{"id":"1808042003","nama":"Bumi Merapi"},{"id":"1808042004","nama":"Banjar Sari"},{"id":"1808042005","nama":"Gunung Katun"},{"id":"1808042006","nama":"Bhakti Negara"},{"id":"1808042007","nama":"Bumi Rejo"},{"id":"1808042008","nama":"Sukosari"},{"id":"1808042010","nama":"Banjar Setia"},{"id":"1808042011","nama":"Gedung Rejo"},{"id":"1808042012","nama":"Banjar Agung"},{"id":"1808042013","nama":"Cugah"},{"id":"1808042014","nama":"Tiuh Balak I"},{"id":"1808042017","nama":"Tiuh Balak"},{"id":"1808042018","nama":"Mekar Asri"},{"id":"1808042019","nama":"Banjar Negara"},{"id":"1808042020","nama":"Banjar Masin"},{"id":"1808042021","nama":"Banjar Mulya"},{"id":"1808042022","nama":"Banjar Baru"}]