[{"id":"3205202001","nama":"Cisurupan"},{"id":"3205202002","nama":"Cidatar"},{"id":"3205202003","nama":"Sukawangi"},{"id":"3205202004","nama":"Sukatani"},{"id":"3205202005","nama":"Situsari"},{"id":"3205202006","nama":"Pakuwon"},{"id":"3205202007","nama":"Balewangi"},{"id":"3205202008","nama":"Sirnajaya"},{"id":"3205202009","nama":"Cisero"},{"id":"3205202010","nama":"Kramatwangi"},{"id":"3205202011","nama":"Cipaganti"},{"id":"3205202012","nama":"Pamulihan"},{"id":"3205202013","nama":"Tambakbaya"},{"id":"3205202014","nama":"Sirnagalih"},{"id":"3205202015","nama":"Pangauban"},{"id":"3205202016","nama":"Simpangsari"},{"id":"3205202017","nama":"Cintaasih"}]