[{"id":"3216130001","nama":"BANTARSARI"},{"id":"3216130002","nama":"BANTARJAYA"},{"id":"3216130003","nama":"KERTASARI"},{"id":"3216130004","nama":"KERTAJAYA"},{"id":"3216130005","nama":"KARANGHAUR"},{"id":"3216130006","nama":"KARANGPATRI"},{"id":"3216130007","nama":"KARANGREJA"},{"id":"3216130008","nama":"KARANGJAYA"},{"id":"3216130009","nama":"SUMBERSARI"},{"id":"3216130010","nama":"SUMBERREJA"},{"id":"3216130011","nama":"SUMBERURIP"},{"id":"3216130012","nama":"KARANGSEGAR"},{"id":"3216130013","nama":"KARANGHARJA"}]