[{"id":"3302142001","nama":"Darmakradenan"},{"id":"3302142002","nama":"Tipar Kidul"},{"id":"3302142003","nama":"Sawangan"},{"id":"3302142004","nama":"Jingkang"},{"id":"3302142005","nama":"Banjarsari"},{"id":"3302142006","nama":"Kalibenda"},{"id":"3302142007","nama":"Pancurendang"},{"id":"3302142008","nama":"Pancasan"},{"id":"3302142009","nama":"Karangbawang"},{"id":"3302142010","nama":"Kracak"},{"id":"3302142011","nama":"Ajibarang Kulon"},{"id":"3302142012","nama":"Ajibarang Wetan"},{"id":"3302142013","nama":"Lesmana"},{"id":"3302142014","nama":"Pandansari"},{"id":"3302142015","nama":"Ciberung"}]