[{"id":"3302212001","nama":"Silado"},{"id":"3302212002","nama":"Karangturi"},{"id":"3302212003","nama":"Karangcegak"},{"id":"3302212004","nama":"Sumbang"},{"id":"3302212005","nama":"Tambaksogra"},{"id":"3302212006","nama":"Kebanggan"},{"id":"3302212007","nama":"Kawungcarang"},{"id":"3302212008","nama":"Karanggintung"},{"id":"3302212009","nama":"Datar"},{"id":"3302212010","nama":"Banjarsari Kulon"},{"id":"3302212011","nama":"Banjarsari Wetan"},{"id":"3302212012","nama":"Banteran"},{"id":"3302212013","nama":"Ciberem"},{"id":"3302212014","nama":"Susukan"},{"id":"3302212015","nama":"Sikapat"},{"id":"3302212016","nama":"Gandatapa"},{"id":"3302212017","nama":"Kotayasa"},{"id":"3302212018","nama":"Limpakuwus"},{"id":"3302212019","nama":"Kedungmalang"}]