[{"id":"3303112001","nama":"Ponjen"},{"id":"3303112002","nama":"Buara"},{"id":"3303112003","nama":"Brakas"},{"id":"3303112004","nama":"Bungkanel"},{"id":"3303112005","nama":"Lumpang"},{"id":"3303112006","nama":"Karanggedang"},{"id":"3303112007","nama":"Kabunderan"},{"id":"3303112008","nama":"Jambudesa"},{"id":"3303112009","nama":"Maribaya"},{"id":"3303112010","nama":"Karanganyar"},{"id":"3303112012","nama":"Banjarkerta"},{"id":"3303112013","nama":"Kalijaran"},{"id":"3303112014","nama":"Kaliori"}]