[{"id":"3310201015","nama":"Jatinom"},{"id":"3310202001","nama":"Beteng"},{"id":"3310202002","nama":"Randulanang"},{"id":"3310202003","nama":"Mranggen"},{"id":"3310202004","nama":"Jemawan"},{"id":"3310202005","nama":"Gedaren"},{"id":"3310202006","nama":"Cawan"},{"id":"3310202007","nama":"Tibayan"},{"id":"3310202008","nama":"Bengking"},{"id":"3310202009","nama":"Temuireng"},{"id":"3310202010","nama":"Bandungan"},{"id":"3310202011","nama":"Kayumas"},{"id":"3310202012","nama":"Socokangsi"},{"id":"3310202013","nama":"Glagah"},{"id":"3310202014","nama":"Krajan"},{"id":"3310202016","nama":"Bonyokan"},{"id":"3310202017","nama":"Pandeyan"},{"id":"3310202018","nama":"Puluhan"}]