[{"id":"3310160001","nama":"TRASAN"},{"id":"3310160002","nama":"SAWAHAN"},{"id":"3310160003","nama":"JUWIRAN"},{"id":"3310160004","nama":"JETIS"},{"id":"3310160005","nama":"KETITANG"},{"id":"3310160006","nama":"GONDANGSARI"},{"id":"3310160007","nama":"SERENAN"},{"id":"3310160008","nama":"TLOGORANDU"},{"id":"3310160009","nama":"BOLOPLERET"},{"id":"3310160010","nama":"TANJUNG"},{"id":"3310160011","nama":"KENAIBAN"},{"id":"3310160012","nama":"BULUREJO"},{"id":"3310160013","nama":"JATEN"},{"id":"3310160014","nama":"MRISEN"},{"id":"3310160015","nama":"PUNDUNGAN"},{"id":"3310160016","nama":"JUWIRING"},{"id":"3310160017","nama":"KWARASAN"},{"id":"3310160018","nama":"CARIKAN"},{"id":"3310160019","nama":"TAJI"}]