[{"id":"3318212001","nama":"Kajar"},{"id":"3318212002","nama":"Trangkil"},{"id":"3318212003","nama":"Pasucen"},{"id":"3318212004","nama":"Tegalharjo"},{"id":"3318212005","nama":"Mojoagung"},{"id":"3318212006","nama":"Ketanen"},{"id":"3318212007","nama":"Karanglegi"},{"id":"3318212008","nama":"Karangwage"},{"id":"3318212009","nama":"Kadilangu"},{"id":"3318212010","nama":"Tlutup"},{"id":"3318212011","nama":"Krandan"},{"id":"3318212012","nama":"Kertomulyo"},{"id":"3318212013","nama":"Rejoagung"},{"id":"3318212014","nama":"Guyangan"},{"id":"3318212015","nama":"Sambilawang"},{"id":"3318212016","nama":"Asempapan"}]