[{"id":"3329090001","nama":"SINDANGHEULA"},{"id":"3329090002","nama":"BLANDONGAN"},{"id":"3329090003","nama":"KERTASARI"},{"id":"3329090004","nama":"BANDUNGSARI"},{"id":"3329090005","nama":"CIPAJANG"},{"id":"3329090006","nama":"PENANGGAPAN"},{"id":"3329090007","nama":"MALAHAYU"},{"id":"3329090008","nama":"CIKUYA"},{"id":"3329090009","nama":"BANJARHARJO"},{"id":"3329090010","nama":"PARIREJA"},{"id":"3329090011","nama":"CIGADUNG"},{"id":"3329090012","nama":"TIWULANDU"},{"id":"3329090013","nama":"CIKAKAK"},{"id":"3329090014","nama":"CIBENDUNG"},{"id":"3329090015","nama":"KARANGMAJA"},{"id":"3329090016","nama":"DUKUHJERUK"},{"id":"3329090017","nama":"PENDE"},{"id":"3329090018","nama":"SUKAREJA"},{"id":"3329090019","nama":"KUBANGJERO"},{"id":"3329090020","nama":"CIBUNIWANGI"},{"id":"3329090021","nama":"CIMUNDING"},{"id":"3329090022","nama":"CIAWI"},{"id":"3329090023","nama":"CIHAUR"},{"id":"3329090024","nama":"TEGALREJA"},{"id":"3329090025","nama":"BANJAR LOR"}]