[{"id":"3374051001","nama":"Sembungharjo"},{"id":"3374051002","nama":"Kudu"},{"id":"3374051003","nama":"Karangroto"},{"id":"3374051004","nama":"Genuksari"},{"id":"3374051005","nama":"Banjardowo"},{"id":"3374051006","nama":"Gebangsari"},{"id":"3374051007","nama":"Trimulyo"},{"id":"3374051008","nama":"Penggaron Lor"},{"id":"3374051009","nama":"Muktiharjo Lor"},{"id":"3374051010","nama":"Bangetayu Kulon"},{"id":"3374051011","nama":"Bangetayu Wetan"},{"id":"3374051012","nama":"Terboyo Kulon"},{"id":"3374051013","nama":"Terboyo Wetan"}]