[{"id":"3522080001","nama":"BABAD"},{"id":"3522080002","nama":"PEJOK"},{"id":"3522080003","nama":"DAYUKIDUL"},{"id":"3522080004","nama":"PANJANG"},{"id":"3522080005","nama":"TONDOMULO"},{"id":"3522080006","nama":"KESONGO"},{"id":"3522080007","nama":"KENDUNG"},{"id":"3522080008","nama":"MLIDEG"},{"id":"3522080009","nama":"TUMBRASANOM"},{"id":"3522080010","nama":"KEDUNGADEM"},{"id":"3522080011","nama":"DUWEL"},{"id":"3522080012","nama":"KEPOH KIDUL"},{"id":"3522080013","nama":"GEGER"},{"id":"3522080014","nama":"KEDUNGREJO"},{"id":"3522080015","nama":"MEGALE"},{"id":"3522080016","nama":"SIDOREJO"},{"id":"3522080017","nama":"DROKILO"},{"id":"3522080018","nama":"MOJOREJO"},{"id":"3522080019","nama":"JAMBEREJO"},{"id":"3522080020","nama":"SIDOMULYO"},{"id":"3522080021","nama":"TLOGOAGUNG"},{"id":"3522080022","nama":"NGRANDU"},{"id":"3522080023","nama":"BALONGCABE"}]