[{"id":"3523190001","nama":"JATISARI"},{"id":"3523190002","nama":"KAYEN"},{"id":"3523190003","nama":"SUKOHARJO"},{"id":"3523190004","nama":"SIDOMULYO"},{"id":"3523190005","nama":"CINGKLUNG"},{"id":"3523190006","nama":"MARGOSUKO"},{"id":"3523190007","nama":"NGAMPELREJO"},{"id":"3523190008","nama":"PUGOH"},{"id":"3523190009","nama":"KARANGREJO"},{"id":"3523190010","nama":"SUMBERAN"},{"id":"3523190011","nama":"SIDING"},{"id":"3523190012","nama":"TENGGER KULON"},{"id":"3523190013","nama":"NGUJURAN"},{"id":"3523190014","nama":"TLOGOAGUNG"},{"id":"3523190015","nama":"LATSARI"},{"id":"3523190016","nama":"SUKOLILO"},{"id":"3523190017","nama":"BULUJOWO"},{"id":"3523190018","nama":"BULUMEDURO"},{"id":"3523190019","nama":"BANJAREJO"},{"id":"3523190020","nama":"TERGAMBANG"},{"id":"3523190021","nama":"SEMBUNGIN"},{"id":"3523190022","nama":"BONCONG"},{"id":"3523190023","nama":"BOGOREJO"},{"id":"3523190024","nama":"BANCAR"}]