[{"id":"3602190008","nama":"CILANGKAP"},{"id":"3602190009","nama":"PASIR KECAPI"},{"id":"3602190012","nama":"MEKARSARI"},{"id":"3602190013","nama":"SANGIANG"},{"id":"3602190014","nama":"TANJUNG SARI"},{"id":"3602190015","nama":"MAJA"},{"id":"3602190016","nama":"CURUG BADAK"},{"id":"3602190017","nama":"PASIR KEMBANG"},{"id":"3602190018","nama":"PADASUKA"},{"id":"3602190019","nama":"GUBUGANCIBEUREUM"},{"id":"3602190020","nama":"BINONG"},{"id":"3602190021","nama":"SINDANGMULYA"},{"id":"3602190022","nama":"BUYUT MEKAR"},{"id":"3602190023","nama":"MAJA BARU"}]