[{"id":"3604322001","nama":"Mancak"},{"id":"3604322002","nama":"Ciwarna"},{"id":"3604322003","nama":"Angsana"},{"id":"3604322004","nama":"Talaga"},{"id":"3604322005","nama":"Cikedung"},{"id":"3604322006","nama":"Sigedong"},{"id":"3604322007","nama":"Sangiang"},{"id":"3604322008","nama":"Pasirwaru"},{"id":"3604322009","nama":"Waringin"},{"id":"3604322010","nama":"Winong"},{"id":"3604322011","nama":"Batukuda"},{"id":"3604322012","nama":"Labuan"},{"id":"3604322013","nama":"Bale Kambang"},{"id":"3604322014","nama":"Bale Kencana"}]