[{"id":"6103110001","nama":"PARE\/SUTIPADANG"},{"id":"6103110002","nama":"TENGUWE"},{"id":"6103110003","nama":"ENKADIK PADE"},{"id":"6103110004","nama":"SEMUNTIK"},{"id":"6103110005","nama":"SEKENDAL"},{"id":"6103110006","nama":"SEPANGAH"},{"id":"6103110007","nama":"SERIMBU"},{"id":"6103110008","nama":"JAMBU TEMBAWANG"},{"id":"6103110009","nama":"DANGE AJI"},{"id":"6103110010","nama":"BENTIANG MADOMANG"},{"id":"6103110011","nama":"TENGOK PELAIK"},{"id":"6103110012","nama":"SEMPATUNG LAWEK"},{"id":"6103110013","nama":"ENGKANGIN"},{"id":"6103110014","nama":"MERAYUH"},{"id":"6103110015","nama":"NYARI"},{"id":"6103110016","nama":"TEMOYOK"}]