[{"id":"6107140001","nama":"TERTUNG"},{"id":"6107140002","nama":"MUNGGUK BANTOK"},{"id":"6107140003","nama":"TANJUNG PURI"},{"id":"6107140004","nama":"BANING KOTA"},{"id":"6107140005","nama":"LADANG"},{"id":"6107140006","nama":"KAPUAS KANAN HULU"},{"id":"6107140007","nama":"KAPUAS KANAN HILIR"},{"id":"6107140008","nama":"KAPUAS KIRI HILIR"},{"id":"6107140009","nama":"KAPUAS KIRI HULU"},{"id":"6107140010","nama":"TELUK KELANSAM"},{"id":"6107140011","nama":"SUNGAI ANA"},{"id":"6107140012","nama":"MARTI GUNA"},{"id":"6107140013","nama":"TANJUNG KELANSAM"},{"id":"6107140014","nama":"ANGGAH JAYA"},{"id":"6107140015","nama":"LALANG BARU"}]