[{"id":"6201040001","nama":"BABUAL BABOTI"},{"id":"6201040002","nama":"TEMPAYUNG"},{"id":"6201040003","nama":"SAKABULIN"},{"id":"6201040004","nama":"KINJIL"},{"id":"6201040005","nama":"KOTA WARINGIN HILIR"},{"id":"6201040006","nama":"RIAM DURIAN"},{"id":"6201040007","nama":"DAWAK"},{"id":"6201040008","nama":"KOTAWARINGIN HULU"},{"id":"6201040009","nama":"LALANG"},{"id":"6201040010","nama":"RUNGUN"},{"id":"6201040011","nama":"KONDANG"},{"id":"6201040012","nama":"SUKAMULYA"},{"id":"6201040013","nama":"SUKAJAYA"},{"id":"6201040015","nama":"SUKA MAKMUR"},{"id":"6201040018","nama":"IPUH BANGUN JAYA"},{"id":"6201040019","nama":"SUMBER MUKTI"},{"id":"6201040020","nama":"PALIH BARU"}]