[{"id":"6311041001","nama":"MURUNG JAMBU"},{"id":"6311041002","nama":"HALUBAU"},{"id":"6311041004","nama":"PANGGUNG"},{"id":"6311041005","nama":"INAN"},{"id":"6311041006","nama":"MURUNG ABUIN"},{"id":"6311041007","nama":"BARUH BAHINU DALAM"},{"id":"6311041008","nama":"BINJAI"},{"id":"6311041009","nama":"TELAGA PURUN"},{"id":"6311041010","nama":"GALOMBANG"},{"id":"6311041011","nama":"MARADAP"},{"id":"6311041012","nama":"BARUH BAHINU LUAR"},{"id":"6311041015","nama":"BUNGIN"},{"id":"6311041016","nama":"LINGSIR"},{"id":"6311041017","nama":"HALUBAU UTARA"},{"id":"6311041018","nama":"TARANGAN"},{"id":"6311041019","nama":"BATU PIRING"}]