[{"id":"6311012001","nama":"Muara Ninian"},{"id":"6311012002","nama":"Hamarung"},{"id":"6311012003","nama":"Juai"},{"id":"6311012004","nama":"Buntu Karau"},{"id":"6311012005","nama":"Bata"},{"id":"6311012006","nama":"Galumbang"},{"id":"6311012007","nama":"Sungai Batung"},{"id":"6311012008","nama":"Sirap"},{"id":"6311012009","nama":"Tigarun"},{"id":"6311012010","nama":"Teluk Bayur"},{"id":"6311012011","nama":"Pamurus"},{"id":"6311012012","nama":"Marias"},{"id":"6311012013","nama":"Lalayau"},{"id":"6311012014","nama":"Mihu"},{"id":"6311012015","nama":"Hukai"},{"id":"6311012016","nama":"Tawahan"},{"id":"6311012017","nama":"Gulinggang"},{"id":"6311012018","nama":"Mungkur Uyam"},{"id":"6311012019","nama":"Panimbaan"},{"id":"6311012020","nama":"Wonorejo"},{"id":"6311012021","nama":"Sumber Rejeki"}]