[{"id":"7202032001","nama":"Tampemadoro"},{"id":"7202032002","nama":"Pandiri"},{"id":"7202032003","nama":"Watuawu"},{"id":"7202032004","nama":"Tambaro"},{"id":"7202032005","nama":"Tagolu"},{"id":"7202032006","nama":"Maliwuko"},{"id":"7202032007","nama":"Silanca"},{"id":"7202032008","nama":"Sepe"},{"id":"7202032009","nama":"Bategencu"},{"id":"7202032010","nama":"Toyado"},{"id":"7202032011","nama":"Tongko"},{"id":"7202032012","nama":"Malei"},{"id":"7202032013","nama":"Sintuwulemba"},{"id":"7202032014","nama":"Labuan"},{"id":"7202032015","nama":"Labuadago"},{"id":"7202032017","nama":"Rato'ombu"}]