[{"id":"7308201001","nama":"Ujung Tanah"},{"id":"7308202002","nama":"Pacubbe"},{"id":"7308202003","nama":"Panyiwi"},{"id":"7308202004","nama":"Latonro"},{"id":"7308202005","nama":"Watu"},{"id":"7308202006","nama":"Nagauleng"},{"id":"7308202007","nama":"Cenrana"},{"id":"7308202008","nama":"Pallime"},{"id":"7308202009","nama":"Laoni"},{"id":"7308202010","nama":"Labotto"},{"id":"7308202011","nama":"Awang Cengrana"},{"id":"7308202012","nama":"Labonge"},{"id":"7308202013","nama":"Ajallase"},{"id":"7308202014","nama":"Pusunge"},{"id":"7308202015","nama":"Pallae"},{"id":"7308202016","nama":"Watangta"}]