[{"id":"7313021001","nama":"Pammana"},{"id":"7313021002","nama":"Cina"},{"id":"7313022003","nama":"Lempa"},{"id":"7313022004","nama":"Patila"},{"id":"7313022005","nama":"Kampiri"},{"id":"7313022006","nama":"Lapauke"},{"id":"7313022007","nama":"Lagosi"},{"id":"7313022008","nama":"Pallawaruka"},{"id":"7313022009","nama":"Wecudai"},{"id":"7313022010","nama":"Lampulung"},{"id":"7313022011","nama":"Watampanua"},{"id":"7313022012","nama":"Tadangpalie"},{"id":"7313022013","nama":"Simpursia"},{"id":"7313022014","nama":"Tobatang"},{"id":"7313022015","nama":"Abbanuangnge"},{"id":"7313022016","nama":"Tonrong Tengnga"}]