[{"id":"7404071001","nama":"LAWULO"},{"id":"7404071002","nama":"SANI SANI"},{"id":"7404071003","nama":"KALOLOA"},{"id":"7404071004","nama":"KONAWEHA"},{"id":"7404071005","nama":"A W A"},{"id":"7404071006","nama":"LAMBOLEMO"},{"id":"7404071007","nama":"TAMBOLI"},{"id":"7404071008","nama":"TOSIBA"},{"id":"7404071009","nama":"AMOMUTU"},{"id":"7404071010","nama":"MALAHA"},{"id":"7404071011","nama":"LATUO"},{"id":"7404071012","nama":"WOWA TAMBOLI"},{"id":"7404071013","nama":"TONGANAPO"},{"id":"7404071014","nama":"ULU KONAWEHA"},{"id":"7404071015","nama":"PUUTAMBOLI"},{"id":"7404071016","nama":"PUU LAWULO"},{"id":"7404071017","nama":"LIKU"},{"id":"7404071018","nama":"MEURA"},{"id":"7404071019","nama":"ULAWENG"}]