[{"id":"8107013001","nama":"TUNAS ILUR"},{"id":"8107013002","nama":"SAGEY"},{"id":"8107013003","nama":"ARMADA"},{"id":"8107013004","nama":"AMARWAWATU"},{"id":"8107013005","nama":"WAISALAN"},{"id":"8107013006","nama":"BASARIN"},{"id":"8107013007","nama":"GOHA"},{"id":"8107013008","nama":"KOTA SIRI"},{"id":"8107013009","nama":"KILKODA"},{"id":"8107013010","nama":"BAS"},{"id":"8107013011","nama":"TUHA"},{"id":"8107013012","nama":"ARAN"},{"id":"8107013013","nama":"MIRAN"},{"id":"8107013014","nama":"RARAT"},{"id":"8107013015","nama":"TINARU"},{"id":"8107013016","nama":"ADAR"},{"id":"8107013017","nama":"KILTUFA"},{"id":"8107013018","nama":"ETARALU"},{"id":"8107013019","nama":"MIRAN MANABAN"},{"id":"8107013020","nama":"MIRAN RUMUAR"},{"id":"8107013021","nama":"MIRAN KILIAN MANABAN"},{"id":"8107013022","nama":"MIRAN KELEDAR"}]