[{"id":"9104172001","nama":"Wanggar Sari","latitude":0,"longitude":0},{"id":"9104172002","nama":"Wiraska","latitude":0,"longitude":0},{"id":"9104172003","nama":"Yaro Makmur","latitude":0,"longitude":0},{"id":"9104172004","nama":"Jaya Mukti","latitude":0,"longitude":0},{"id":"9104172005","nama":"Wanggar Pantai","latitude":0,"longitude":0},{"id":"9104172006","nama":"Ororodo","latitude":0,"longitude":0},{"id":"9104172007","nama":"Bomopai","latitude":0,"longitude":0},{"id":"9104172008","nama":"Parauto","latitude":0,"longitude":0}]