[{"id":"9118132001","nama":"Yetsy","latitude":0,"longitude":0},{"id":"9118132002","nama":"Powetsy","latitude":0,"longitude":0},{"id":"9118132003","nama":"Pau","latitude":0,"longitude":0},{"id":"9118132004","nama":"Sisakem","latitude":0,"longitude":0},{"id":"9118132005","nama":"Akamar","latitude":0,"longitude":0},{"id":"9118132006","nama":"Birak","latitude":0,"longitude":0},{"id":"9118132007","nama":"Katew","latitude":0,"longitude":0},{"id":"9118132008","nama":"Dawer","latitude":0,"longitude":0}]